odoo/addons/ssi_stock_valuation_layer_recomputation/README.rst
odoo/addons/ssi_stock_valuation_layer_recomputation/__init__.py
odoo/addons/ssi_stock_valuation_layer_recomputation/__manifest__.py
odoo/addons/ssi_stock_valuation_layer_recomputation/menu.xml
odoo/addons/ssi_stock_valuation_layer_recomputation/data/approval_template_data.xml
odoo/addons/ssi_stock_valuation_layer_recomputation/data/base_automation_data.xml
odoo/addons/ssi_stock_valuation_layer_recomputation/data/ir_actions_server_data.xml
odoo/addons/ssi_stock_valuation_layer_recomputation/data/ir_sequence_data.xml
odoo/addons/ssi_stock_valuation_layer_recomputation/data/policy_template_data.xml
odoo/addons/ssi_stock_valuation_layer_recomputation/data/sequence_template_data.xml
odoo/addons/ssi_stock_valuation_layer_recomputation/models/__init__.py
odoo/addons/ssi_stock_valuation_layer_recomputation/models/svl_recomputation.py
odoo/addons/ssi_stock_valuation_layer_recomputation/models/svl_recomputation_type.py
odoo/addons/ssi_stock_valuation_layer_recomputation/security/ir.model.access.csv
odoo/addons/ssi_stock_valuation_layer_recomputation/security/ir_module_category_data.xml
odoo/addons/ssi_stock_valuation_layer_recomputation/security/ir_rule_data.xml
odoo/addons/ssi_stock_valuation_layer_recomputation/security/res_group_data.xml
odoo/addons/ssi_stock_valuation_layer_recomputation/static/description/icon.png
odoo/addons/ssi_stock_valuation_layer_recomputation/views/svl_recomputation_type_views.xml
odoo/addons/ssi_stock_valuation_layer_recomputation/views/svl_recomputation_views.xml
odoo14_addon_ssi_stock_valuation_layer_recomputation-14.0.1.0.0.dist-info/METADATA
odoo14_addon_ssi_stock_valuation_layer_recomputation-14.0.1.0.0.dist-info/WHEEL
odoo14_addon_ssi_stock_valuation_layer_recomputation-14.0.1.0.0.dist-info/top_level.txt
odoo14_addon_ssi_stock_valuation_layer_recomputation-14.0.1.0.0.dist-info/RECORD
