Metadata-Version: 2.1
Name: odoo14-addon-ssi-stock-valuation-layer-recomputation
Version: 14.0.1.0.0
Summary: Stock Valuation Layer Usage Recomputation
Home-page: https://simetri-sinergi.id
Author: PT. Simetri Sinergi Indonesia, OpenSynergy Indonesia
License: AGPL-3
Platform: UNKNOWN
Classifier: Programming Language :: Python
Classifier: Framework :: Odoo
Classifier: Framework :: Odoo :: 14.0
Classifier: License :: OSI Approved :: GNU Affero General Public License v3
Requires-Python: >=3.6
Requires-Dist: odoo14-addon-ssi-m2o-configurator-mixin
Requires-Dist: odoo14-addon-ssi-master-data-mixin
Requires-Dist: odoo14-addon-ssi-product
Requires-Dist: odoo14-addon-ssi-stock-account
Requires-Dist: odoo14-addon-ssi-transaction-confirm-mixin
Requires-Dist: odoo14-addon-ssi-transaction-queue-cancel-mixin
Requires-Dist: odoo14-addon-ssi-transaction-queue-done-mixin
Requires-Dist: odoo <14.1dev,>=14.0a
